{
  "hero": {
    "title": "2025 OCP Global Summit",
    "date": "October 13–16, 2025",
    "dateLayout": true,
    "time": "",
    "buttons": {
      "registerButton": {
        "text": "Register Now",
        "display": true
      },
      "loginButton": {
        "text": "Log In",
        "display": true
      }
    },
    "images": [
      {
        "src": "ocp25g-fnv-header-r_v1.png"
      }
    ],
    "background": {
      "src": "ocp25g-fnv-header-l_v1.png"
    }
  },
  "countdown": {
    "display": true,
    "text": "Event Kickoff"
  },
  "widgets": {
    "schedule": {
      "display": false,
      "title": "Full Event Schedule"
    },
    "disqus": {
      "display": false,
      "title": "Join the Conversation"
    },
    "image": {
      "display": true,
      "title": "",
      "image": {
        "src": "ocp25g-fnv-hlschedule_v1.jpg"
      }
    },
    "content": {
      "display": false,
      "body": ""
    }
  },
  "masonry": {
    "display": true,
    "items": [
      {
        "placement": "Top Left",
        "size": 1,
        "images": [
          {
            "src": "ocp25g-fnv-marketing-space1-v1.png",
            "link": "https://www.opencompute.org/summit/global-summit/theme"
          }
        ]
      },
      {
        "placement": "Top Right",
        "size": 1,
        "images": [
          {
            "src": "ocp25g-fnv-marketing-space2-v1.png",
            "link": "https://www.opencompute.org/membership/how-to-join"
          }
        ]
      },
      {
        "placement": "Bottom Left",
        "size": 1,
        "images": [
          {
            "src": "ocp25g-fnv-marketing-space3-v1.png",
            "link": "https://www.opencompute.org/events/past-events/2025-ocp-emea-summit"
          }
        ]
      },
      {
        "placement": "Bottom Right",
        "size": 1,
        "images": [
          {
            "src": "ocp25g-fnv-marketing-space4-v1.png"
          }
        ]
      }
    ]
  }
}
